canonical_huffman/__init__.py
canonical_huffman/dictionary.py
canonical_huffman/huffman_compression.py
canonical_huffman/huffman_demo.py
canonical_huffman/node.py
canonical_huffman/padded_binary.py
canonical_huffman_compression-0.1.1.8.dist-info/LICENSE
canonical_huffman_compression-0.1.1.8.dist-info/METADATA
canonical_huffman_compression-0.1.1.8.dist-info/WHEEL
canonical_huffman_compression-0.1.1.8.dist-info/top_level.txt
canonical_huffman_compression-0.1.1.8.dist-info/RECORD
