Metadata-Version: 2.1
Name: canonical_huffman_compression
Version: 0.1.1.8
Summary: A package for canonical Huffman compression
Home-page: https://github.com/craigwatkins/Huffman-Compression
Author: Craig Watkins
Author-email: craigwatkinsdev@gmail.com
License: MIT
Keywords: huffman compression canonical
Platform: UNKNOWN
Classifier: Development Status :: 3 - Alpha
Classifier: Intended Audience :: Developers
Classifier: License :: OSI Approved :: MIT License
Classifier: Programming Language :: Python :: 3
Classifier: Programming Language :: Python :: 3.6
Classifier: Programming Language :: Python :: 3.7
Classifier: Programming Language :: Python :: 3.8
Classifier: Programming Language :: Python :: 3.9
Requires-Python: >=3.6
License-File: LICENSE
